fovus/__init__.py
fovus/root_config.py
fovus/adapter/__init__.py
fovus/adapter/fovus_api_adapter.py
fovus/adapter/fovus_cognito_adapter.py
fovus/adapter/fovus_s3_adapter.py
fovus/adapter/fovus_sign_in_adapter.py
fovus/cli/__init__.py
fovus/cli/fovus_cli.py
fovus/cli/helpers.py
fovus/cli/ssl.py
fovus/commands/__init__.py
fovus/commands/auth/__init__.py
fovus/commands/auth/auth_command.py
fovus/commands/auth/commands/__init__.py
fovus/commands/auth/commands/login/__init__.py
fovus/commands/auth/commands/login/auth_login_command.py
fovus/commands/auth/commands/logout/__init__.py
fovus/commands/auth/commands/logout/auth_logout_command.py
fovus/commands/auth/commands/user/__init__.py
fovus/commands/auth/commands/user/auth_user_command.py
fovus/commands/config/__init__.py
fovus/commands/config/config_command.py
fovus/commands/config/commands/__init__.py
fovus/commands/config/commands/open/__init__.py
fovus/commands/config/commands/open/config_open_command.py
fovus/commands/job/__init__.py
fovus/commands/job/job_command.py
fovus/commands/job/commands/__init__.py
fovus/commands/job/commands/create/__init__.py
fovus/commands/job/commands/create/job_create_command.py
fovus/commands/job/commands/delete/__init__.py
fovus/commands/job/commands/delete/job_delete_command.py
fovus/commands/job/commands/download/__init__.py
fovus/commands/job/commands/download/job_download_command.py
fovus/commands/job/commands/live_tail/__init__.py
fovus/commands/job/commands/live_tail/job_live_tail_command.py
fovus/commands/job/commands/status/__init__.py
fovus/commands/job/commands/status/job_status_command.py
fovus/commands/job/commands/sync_files/__init__.py
fovus/commands/job/commands/sync_files/job_sync_command.py
fovus/commands/projects/__init__.py
fovus/commands/projects/projects_command.py
fovus/commands/projects/commands/__init__.py
fovus/commands/projects/commands/list/__init__.py
fovus/commands/projects/commands/list/projects_list_command.py
fovus/commands/storage/__init__.py
fovus-2.8.dist-info/LICENSE.txt
fovus-2.8.dist-info/METADATA
fovus-2.8.dist-info/WHEEL
fovus-2.8.dist-info/entry_points.txt
fovus-2.8.dist-info/top_level.txt
fovus-2.8.dist-info/RECORD
