Metadata-Version: 2.2
Name: fovus
Version: 2.8
Summary: The Fovus Python CLI
Author: Fovus Corporation
Requires-Python: >=3.9
License-File: LICENSE.txt
Requires-Dist: boto3>=1.35.16
Requires-Dist: mypy_boto3_s3>=1.28.36
Requires-Dist: mypy_boto3_cognito_idp>=1.28.36
Requires-Dist: dateparser>=1.1.8
Requires-Dist: jsonschema>=3.2.0
Requires-Dist: pycognito>=2023.5.0
Requires-Dist: requests>=2.32.3
Requires-Dist: tqdm>=4.59.0
Requires-Dist: packaging>=23.1
Requires-Dist: typing_extensions<5,>=4.7.1
Requires-Dist: websockets>=11.0.3
Requires-Dist: setuptools>=68.2.2
Requires-Dist: termcolor>=2.4.0
Requires-Dist: paramiko>=3.4.1
Requires-Dist: urllib3!=2.0.*,!=2.1.*,!=2.2.0,!=2.2.1,>=1.26.20; python_version < "3.10"
Requires-Dist: urllib3>=2.2.2; python_version >= "3.10"
Requires-Dist: certifi>=2024.8.30
Requires-Dist: click>=8.1.7
Provides-Extra: dev
Requires-Dist: autoflake; extra == "dev"
Requires-Dist: bandit; extra == "dev"
Requires-Dist: black; extra == "dev"
Requires-Dist: flake8; extra == "dev"
Requires-Dist: isort; extra == "dev"
Requires-Dist: mypy; extra == "dev"
Requires-Dist: pre-commit; extra == "dev"
Requires-Dist: pycodestyle; extra == "dev"
Requires-Dist: pydocstyle; extra == "dev"
Requires-Dist: pydocstringformatter; extra == "dev"
Requires-Dist: pylint; extra == "dev"
Requires-Dist: pyupgrade; extra == "dev"
Requires-Dist: types-requests; extra == "dev"
Requires-Dist: types-dateparser; extra == "dev"
Provides-Extra: test
Requires-Dist: coverage; extra == "test"
Provides-Extra: deploy
Requires-Dist: build; extra == "deploy"
Requires-Dist: pyarmor; extra == "deploy"
Requires-Dist: twine; extra == "deploy"
Dynamic: author
Dynamic: description
Dynamic: description-content-type
Dynamic: provides-extra
Dynamic: requires-dist
Dynamic: requires-python
Dynamic: summary
